sugaru/__init__.py
sugaru/__main__.py
sugaru/file_loader/__init__.py
sugaru/file_loader/logging.py
sugaru/file_loader/simple_json/__init__.py
sugaru/file_loader/simple_yaml/__init__.py
sugaru/file_loader/simple_yaml/loader.py
sugaru/file_loader/types.py
sugaru/file_writer/__init__.py
sugaru/file_writer/logging.py
sugaru/file_writer/simple_json/__init__.py
sugaru/file_writer/simple_yaml/__init__.py
sugaru/file_writer/types.py
sugaru/interfaces.py
sugaru/logging.py
sugaru/object_loader/__init__.py
sugaru/object_loader/module_loader.py
sugaru/object_loader/object_creator.py
sugaru/object_loader/objects_loader.py
sugaru/object_loader/simple_loader.py
sugaru/plugin_executor/__init__.py
sugaru/plugin_executor/executor.py
sugaru/py.typed
sugaru/sugarator.py
sugaru/types.py
sugaru/utils/__init__.py
sugaru/utils/encode_decode.py
sugaru/utils/names_and_types.py
sugaru/utils/object_loading.py
sugaru/utils/signature.py
sugaru-0.3.1.dist-info/LICENSE
sugaru-0.3.1.dist-info/METADATA
sugaru-0.3.1.dist-info/WHEEL
sugaru-0.3.1.dist-info/RECORD
